flask_request_id_header_middleware/__init__.py
flask_request_id_header_middleware/log_filter.py
flask_request_id_header_middleware/request_id.py
flask_request_id_header_middleware/requests_patch.py
flask_request_id_header_middleware-0.0.2.dist-info/LICENSE
flask_request_id_header_middleware-0.0.2.dist-info/METADATA
flask_request_id_header_middleware-0.0.2.dist-info/WHEEL
flask_request_id_header_middleware-0.0.2.dist-info/top_level.txt
flask_request_id_header_middleware-0.0.2.dist-info/RECORD
