Metadata-Version: 2.1
Name: flask-request-id-header-middleware
Version: 0.0.2
Summary: Python Flask Middleware to log and set Request ID in the HTTP header
Home-page: UNKNOWN
Author: Shatrugna Rao Korukanti
Author-email: shatrugna_korukanti@tecnics.com
License: MIT
Platform: UNKNOWN
Classifier: Development Status :: 3 - Alpha
Classifier: Framework :: Flask
Classifier: Intended Audience :: Developers
Classifier: Operating System :: OS Independent
Classifier: Programming Language :: Python :: 3
Classifier: Topic :: Software Development :: Libraries :: Python Modules
License-File: LICENSE
Requires-Dist: Flask
